HISTORY.txt
MANIFEST.in
README.rst
setup.cfg
setup.py
por/__init__.py
por.karma.egg-info/PKG-INFO
por.karma.egg-info/SOURCES.txt
por.karma.egg-info/dependency_links.txt
por.karma.egg-info/entry_points.txt
por.karma.egg-info/namespace_packages.txt
por.karma.egg-info/not-zip-safe
por.karma.egg-info/requires.txt
por.karma.egg-info/top_level.txt
por/karma/__init__.py
por/karma/events.py
por/karma/models.py