Metadata-Version: 1.1
Name: por.karma
Version: 1.0
Summary: Karma integration in Penelope
Home-page: http://www.redturtle.it
Author: RedTurtle
Author-email: svilplone@redturtle.it
License: GPL
Keywords: penelope karma trac
Platform: UNKNOWN
Classifier: Programming Language :: Python
